edc_glucose/__init__.py
edc_glucose/apps.py
edc_glucose/constants.py
edc_glucose/fieldsets.py
edc_glucose/list_filters.py
edc_glucose/models.py
edc_glucose/utils.py
edc_glucose/form_validators/__init__.py
edc_glucose/form_validators/fasting_form_validator.py
edc_glucose/form_validators/fbg_form_validator_mixin.py
edc_glucose/form_validators/fbg_ogtt_form_validator_mixin.py
edc_glucose/form_validators/glucose_form_validator.py
edc_glucose/form_validators/glucose_form_validator_mixin.py
edc_glucose/form_validators/ogtt_form_validator_mixin.py
edc_glucose/migrations/__init__.py
edc_glucose/model_mixins/__init__.py
edc_glucose/model_mixins/fasting_model_mixin.py
edc_glucose/model_mixins/fbg_model_mixin.py
edc_glucose/model_mixins/glucose_model_mixin.py
edc_glucose/model_mixins/hba1c_model_mixin.py
edc_glucose/model_mixins/ogtt_model_mixin.py
edc_glucose/tests/__init__.py
edc_glucose/tests/consents.py
edc_glucose/tests/models.py
edc_glucose/tests/test_settings.py
edc_glucose/tests/urls.py
edc_glucose/tests/visit_schedules.py
edc_glucose/tests/etc/user-aes-local.key
edc_glucose/tests/etc/user-aes-restricted.key
edc_glucose/tests/etc/user-rsa-local-private.pem
edc_glucose/tests/etc/user-rsa-local-public.pem
edc_glucose/tests/etc/user-rsa-restricted-private.pem
edc_glucose/tests/etc/user-rsa-restricted-public.pem
edc_glucose/tests/etc/user-salt-local.key
edc_glucose/tests/etc/user-salt-restricted.key
edc_glucose/tests/tests/__init__.py
edc_glucose/tests/tests/test_glucose_form_validator.py
edc_glucose-1.0.3.dist-info/licenses/AUTHORS.rst
edc_glucose-1.0.3.dist-info/licenses/LICENSE
edc_glucose-1.0.3.dist-info/METADATA
edc_glucose-1.0.3.dist-info/WHEEL
edc_glucose-1.0.3.dist-info/top_level.txt
edc_glucose-1.0.3.dist-info/RECORD
